clubear/__init__.py
clubear/ck.py
clubear/dm.py
clubear/fun.py
clubear/md.py
clubear/pm.py
clubear/pt.py
clubear/sf.py
clubear/sim.py
clubear-0.0.32.dist-info/LICENSE
clubear-0.0.32.dist-info/METADATA
clubear-0.0.32.dist-info/WHEEL
clubear-0.0.32.dist-info/top_level.txt
clubear-0.0.32.dist-info/RECORD
