Metadata-Version: 2.1
Name: clubear
Version: 0.0.32
Summary: Subsample-based Model and Research Toolkit.
Home-page: UNKNOWN
Author: Hansheng Wang
Author-email: hansheng@gsm.pku.edu.cn
License: UNKNOWN
Platform: UNKNOWN
Classifier: Development Status :: 3 - Alpha
Classifier: Intended Audience :: Developers
Classifier: Programming Language :: Python :: 3
Requires-Dist: IPython
Requires-Dist: matplotlib
Requires-Dist: numpy
Requires-Dist: pandas
Requires-Dist: scipy
Requires-Dist: seaborn
Requires-Dist: sklearn
